README.md
setup.py
uglifyc/__init__.py
uglifyc/main.py
uglifyc.egg-info/PKG-INFO
uglifyc.egg-info/SOURCES.txt
uglifyc.egg-info/dependency_links.txt
uglifyc.egg-info/entry_points.txt
uglifyc.egg-info/requires.txt
uglifyc.egg-info/top_level.txt