Metadata-Version: 2.1
Name: uglifyc
Version: 0.1.3
Summary: Uglify C code
Home-page: https://github.com/Muxutruk2/uglify
Author: Muxutruk
Author-email: 156070698+Muxutruk2@users.noreply.github.com
Classifier: Programming Language :: Python :: 3
Classifier: License :: OSI Approved :: MIT License
Classifier: Operating System :: OS Independent
Requires-Python: >=3.12
Requires-Dist: click
